audits/__init__.py
audits/admin.py
audits/apps.py
audits/models.py
audits/tests.py
audits/views.py
audits/migrations/0001_initial.py
audits/migrations/__init__.py
django_model_auditor-0.0.4.dist-info/METADATA
django_model_auditor-0.0.4.dist-info/WHEEL
django_model_auditor-0.0.4.dist-info/top_level.txt
django_model_auditor-0.0.4.dist-info/RECORD
