Metadata-Version: 2.1
Name: django-model-auditor
Version: 0.0.4
Summary: An extension to the Django web framework that provides version control for model instances.
Home-page: UNKNOWN
Author: vishalagrawal
Author-email: 
License: UNKNOWN
Platform: UNKNOWN
Requires-Python: >=3.8
Requires-Dist: Django (>=3.0)
Requires-Dist: dictdiffer (>=0.8.1)
